perun/connector/__init__.py
perun/connector/adapters/AdapterInterface.py
perun/connector/adapters/AdaptersManager.py
perun/connector/adapters/LdapAdapter.py
perun/connector/adapters/PerunRpcAdapter.py
perun/connector/adapters/__init__.py
perun/connector/config_templates/__init__.py
perun/connector/connectors/LdapConnector.py
perun/connector/connectors/__init__.py
perun/connector/models/Facility.py
perun/connector/models/Group.py
perun/connector/models/HasIdAbstract.py
perun/connector/models/Member.py
perun/connector/models/MemberStatusEnum.py
perun/connector/models/Resource.py
perun/connector/models/User.py
perun/connector/models/UserExtSource.py
perun/connector/models/VO.py
perun/connector/models/__init__.py
perun/connector/perun_openapi/__init__.py
perun/connector/perun_openapi/api_client.py
perun/connector/perun_openapi/configuration.py
perun/connector/perun_openapi/exceptions.py
perun/connector/perun_openapi/model_utils.py
perun/connector/perun_openapi/rest.py
perun/connector/perun_openapi/api/__init__.py
perun/connector/perun_openapi/api/attributes_manager_api.py
perun/connector/perun_openapi/api/audit_messages_manager_api.py
perun/connector/perun_openapi/api/authz_resolver_api.py
perun/connector/perun_openapi/api/cabinet_manager_api.py
perun/connector/perun_openapi/api/consents_manager_api.py
perun/connector/perun_openapi/api/database_manager_api.py
perun/connector/perun_openapi/api/ext_sources_manager_api.py
perun/connector/perun_openapi/api/facilities_manager_api.py
perun/connector/perun_openapi/api/groups_manager_api.py
perun/connector/perun_openapi/api/integration_manager_api.py
perun/connector/perun_openapi/api/members_manager_api.py
perun/connector/perun_openapi/api/owners_manager_api.py
perun/connector/perun_openapi/api/registrar_manager_api.py
perun/connector/perun_openapi/api/resources_manager_api.py
perun/connector/perun_openapi/api/rt_messages_manager_api.py
perun/connector/perun_openapi/api/searcher_api.py
perun.connector-3.11.0.dist-info/LICENSE
perun.connector-3.11.0.dist-info/METADATA
perun.connector-3.11.0.dist-info/WHEEL
perun.connector-3.11.0.dist-info/top_level.txt
perun.connector-3.11.0.dist-info/RECORD
